{
  "items": {
    "weuq-0001": {
      "id": "weuq-0001",
      "title": "9 Story Building: Sampling Analysis",
      "base": "weuq-0001",
      "doc": [
        "weuq-0001/figures/9story-GI.png",
        "weuq-0001/README.rst",
        "weuq-0001/figures/9story-EDP-Reliability.png",
        "weuq-0001/figures/9story-SIM1.png",
        "weuq-0001/figures/9Story.png",
        "weuq-0001/figures/9story-RV.png",
        "weuq-0001/figures/9story-FEM.png",
        "weuq-0001/../weuq-0002/src/FramePost.py",
        "weuq-0001/figures/9story-RES1.png",
        "weuq-0001/figures/9story-RES-Reliability.png",
        "weuq-0001/figures/9story-UQ-Reliability.png",
        "weuq-0001/figures/9story-RES-USER.png",
        "weuq-0001/../weuq-0002/src/FrameRecorder.tcl",
        "weuq-0001/figures/9story-EDP-USER.png",
        "weuq-0001/src/Frame9Model.tcl",
        "weuq-0001/figures/9story-SIM2.png",
        "weuq-0001/figures/9story-RES6.png",
        "weuq-0001/../weuq-0002/src/FramePost.tcl",
        "weuq-0001/figures/9story-UQ.png",
        "weuq-0001/figures/9story-EVENT.png",
        "weuq-0001/figures/9story-RES2.png"
      ],
      "entry_point": "weuq-0001/./input.json",
      "summary": "Forward propagation of a 9-story frame with stochastic wind loading and default EDPs.",
      "logo": "figures/9Story.png",
      "published": "2020-12-17T21:26:53.946381-08:00",
      "categories": {
        "Difficulty": "0",
        "Simulation": "OpenSees-Simulation"
      },
      "tags": [
        "UV.1.1",
        "UM.1.1.1",
        "UM.1.1"
      ]
    },
    "weuq-0002": {
      "id": "weuq-0002",
      "base": "weuq-0002",
      "title": "9-Story Building: Sensitivity with user-defined EDPs",
      "published": "2021-03-17T21:26:53.946381-08:00\"",
      "doc": [],
      "categories": {
        "Difficulty": "0",
        "Simulation": "OpenSees-Simulation"
      },
      "tags": [
        "UV.1.1",
        "UM.1.1.1",
        "UM.1.1"
      ]
    },
    "weuq-0003": {
      "id": "weuq-0003",
      "base": "weuq-0003",
      "title": "9-Story Building: Reliability",
      "published": "2021-03-17T21:26:53.946381-08:00\"",
      "doc": [],
      "categories": {
        "Difficulty": "0",
        "Simulation": "OpenSees-Simulation"
      },
      "tags": [
        "UV.1.1",
        "UM.1.1.1",
        "UM.1.1"
      ]
    },
    "weuq-0007": {
      "id": "weuq-0007",
      "title": "3 Story Building: Sensitivity Analysis",
      "base": "weuq-0007",
      "doc": [
        "weuq-0007/postprocess.py",
        "weuq-0007/README.rst",
        "weuq-0007/figures/9story-RES-USER.png",
        "weuq-0007/figures/9story-RES6.png",
        "weuq-0007/figures/9story-RES-Reliability.png",
        "weuq-0007/3Story.tcl",
        "weuq-0007/figures/9story-UQ-Reliability.png",
        "weuq-0007/figures/weuq-0007-FEM.png",
        "weuq-0007/postprocess.tcl",
        "weuq-0007/figures/9story-RES1.png",
        "weuq-0007/figures/weuq-0007-UQ.png",
        "weuq-0007/figures/9story-EDP-USER.png",
        "weuq-0007/figures/weuq-0007-EVT.png",
        "weuq-0007/figures/3story.png",
        "weuq-0007/figures/weuq-0007-GI.png",
        "weuq-0007/figures/9story-RES2.png",
        "weuq-0007/recorder.tcl",
        "weuq-0007/figures/9story-RV.png",
        "weuq-0007/figures/9story-EDP-Reliability.png",
        "weuq-0007/figures/weuq-0007-SIM.png"
      ],
      "entry_point": "weuq-0007/./input.json",
      "summary": "This study uses WE-UQ's built-in interface to the TPU wind tunel datasets in the analysis of a 3 story building with quantified uncertainty.",
      "logo": "figures/3story.png",
      "published": "2021-03-17T21:26:53.946381-08:00",
      "categories": {
        "Difficulty": "0",
        "Simulation": "OpenSees-Simulation"
      },
      "tags": [
        "UV.1.1",
        "UM.1.1.1",
        "UM.1.1"
      ]
    },
    "weuq-0012": {
      "id": "weuq-0012",
      "base": "weuq-0012",
      "title": "Wind Tunnel-Informed Stochastic Wind Load Generation",
      "published": "2023-05-26T21:26:53.946381-08:00\"",
      "doc": [
          "weuq-0012/README.rst",   
          "weuq-0012/figures/we12_1.png",
          "weuq-0012/figures/we12_2.png",
          "weuq-0012/figures/we12_3.png",
          "weuq-0012/figures/we12_UQ.png",
          "weuq-0012/figures/we12_GI.png",
          "weuq-0012/figures/we12_SIM.png",
          "weuq-0012/figures/we12_EVT.png",
          "weuq-0012/figures/we12_RV.png",
          "weuq-0012/figures/we12_RES1.png",
          "weuq-0012/figures/we12_RES2.png",
          "weuq-0012/figures/we12_RES3.png"    
      ],
      "entry_point": "weuq-0012/./input.json",
      "summary": "This study estimates the uncertainty in structural responses subjected to wind tunnel-informed stochastic wind load.",
      "logo": "figures/we12_1.png",
      "categories": {
        "Difficulty": "0",
        "Simulation": "OpenSees-Simulation"
      },
      "tags": [
      ]
    },
    "weuq-0011": {
      "id": "weuq-0011",
      "base": "weuq-0011",
      "title": "Digital Wind Tunnel I: Empty Domain Simulation",
      "published": "2022-03-06T21:26:53.946381-08:00\"",
      "doc": [
          "weuq-0011/README.rst",   
          "weuq-0011/figures/UFWindTunnel.png",
          "weuq-0011/figures/openfoam_structure.png",
          "weuq-0011/figures/DWTsketch.png",
          "weuq-0011/figures/User-interface.png",   
          "weuq-0011/figures/Direct_table.png",
          "weuq-0011/figures/Mesh.png",   
          "weuq-0011/figures/table.png",
          "weuq-0011/figures/TInF_function.png",
          "weuq-0011/figures/Post-processsing.png"    
      ],
      "entry_point": "weuq-0011/./input.json",
      "summary": "This study uses WE-UQ's built-in interface 'Digital Wind Tunnel' to run a CFD simulation.",
      "logo": "figures/DWTsketch.png",
      "categories": {
        "Difficulty": "0",
        "Simulation": "OpenSees-Simulation"
      },
      "tags": [
        "UV.1.1",
        "UM.1.1.1",
        "UM.1.1"
      ]
    },
    "weuq-0013": {
      "id": "weuq-0013",
      "base": "weuq-0013",
      "title": "Digital Wind Tunnel II: Wind Load on Isolated Building with Simple Geometry",
      "doc": [
          "weuq-0013/README.rst",   
          "weuq-0013/figures/we13_CFD_Results_StreamLines.svg",
          "weuq-0013/figures/we13_computational_domain.svg",
          "weuq-0013/figures/we13_CFD_Results.svg",
          "weuq-0013/figures/we13_EDP_panel.svg",
          "weuq-0013/figures/we13_EVT_BoundaryConditions.svg",
          "weuq-0013/figures/we13_EVT_Geometry_tab.svg",
          "weuq-0013/figures/we13_EVT_Mesh_AdvancedOptions.svg",
          "weuq-0013/figures/we13_EVT_Mesh_EdgeRefinement_tab.svg",
          "weuq-0013/figures/we13_EVT_Mesh_PrismLayers_tab.svg",
          "weuq-0013/figures/we13_EVT_Mesh_RegionalRefinement_tab.svg",
          "weuq-0013/figures/we13_EVT_Mesh_Run.svg",
          "weuq-0013/figures/we13_EVT_Mesh_SurfaceRefinement_tab.svg",
          "weuq-0013/figures/we13_EVT_Mesh_View.svg",
          "weuq-0013/figures/we13_EVT_Mesh_tab.svg",
          "weuq-0013/figures/we13_EVT_Monitoring.svg",
          "weuq-0013/figures/we13_EVT_NumericalSetup.svg",
          "weuq-0013/figures/we13_EVT_RegionalRefinement_tab.svg",
          "weuq-0013/figures/we13_EVT_Start_tab.svg",
          "weuq-0013/figures/we13_FEM_panel.svg",
          "weuq-0013/figures/we13_GI_panel.svg",
          "weuq-0013/figures/we13_MonitorJob.svg",
          "weuq-0013/figures/we13_RES_DataValues.svg",
          "weuq-0013/figures/we13_RES_Summary.svg",
          "weuq-0013/figures/we13_RV_panel.svg",
          "weuq-0013/figures/we13_RunJob.svg",
          "weuq-0013/figures/we13_SIM_panel.svg",
          "weuq-0013/figures/we13_UQ_panel.svg",
          "weuq-0013/figures/we13_mean_velocity_profile_fitting.svg",
          "weuq-0013/figures/we13_tpu_building_demo.jpg"  
      ],
      "entry_point": "weuq-0013/./input.json",
      "summary": "This example demonstrates application of CFD to simulate wind loads on buildings for estimating the resulting structural responses",
      "logo": "we13_CFD_Results_StreamLines.svg",
      "published": "2023-08-12T21:26:53.946381-08:00\"",
      "categories": {
        "Difficulty": "0",
        "Simulation": "OpenSees-Simulation"
      },
      "tags": [
      ]
    },
    "weuq-0014": {
      "id": "weuq-0014",
      "base": "weuq-0014",
      "title": "Digital Wind Tunnel II: Wind Load on Isolated Building with Complicated Geometry",
      "doc": [
          "weuq-0014/README.rst",   
          "weuq-0014/figures/we14_CFD_Results.svg",
          "weuq-0014/figures/we14_EDP_panel.svg",
          "weuq-0014/figures/we14_EVT_BoundaryConditions.svg",
          "weuq-0014/figures/we14_EVT_Geometry_tab.svg",
          "weuq-0014/figures/we14_EVT_Import_stl.svg",
          "weuq-0014/figures/we14_EVT_Mesh_EdgeRefinement_tab.svg",
          "weuq-0014/figures/we14_EVT_Mesh_PrismLayers_tab.svg",
          "weuq-0014/figures/we14_EVT_Mesh_RegionalRefinement_tab.svg",
          "weuq-0014/figures/we14_EVT_Mesh_SurfaceRefinement_tab.svg",
          "weuq-0014/figures/we14_EVT_Mesh_View.svg",
          "weuq-0014/figures/we14_EVT_Mesh_tab.svg",
          "weuq-0014/figures/we14_EVT_Monitoring.svg",
          "weuq-0014/figures/we14_EVT_NumericalSetup.svg",
          "weuq-0014/figures/we14_EVT_RegionalRefinement_tab.svg",
          "weuq-0014/figures/we14_EVT_Start_tab.svg",
          "weuq-0014/figures/we14_FEM_panel.svg",
          "weuq-0014/figures/we14_GI_panel.svg",
          "weuq-0014/figures/we14_RES_DataValues.svg",
          "weuq-0014/figures/we14_RES_Summary.svg",
          "weuq-0014/figures/we14_RV_panel.svg",
          "weuq-0014/figures/we14_RunJob.svg",
          "weuq-0014/figures/we14_SIM_panel.svg",
          "weuq-0014/figures/we14_UQ_panel.svg",
          "weuq-0014/figures/we14_study_building.svg"
      ],
      "entry_point": "weuq-0014/./input.json",
      "summary": "This example demonstrates application of CFD for generating wind loads on complex shaped buildings and estimating the resulting structural responses",
      "logo": "we14_CFD_Results_StreamLines.svg",
      "published": "2023-09-12T21:30:53.946381-08:00\"",
      "categories": {
        "Difficulty": "0",
        "Simulation": "OpenSees-Simulation"
      },
      "tags": [
      ]
    },
    "weuq-0015": {
      "id": "weuq-0015",
      "base": "weuq-0015",
      "title": "Digital Wind Tunnel II: Calibrating ABL flows with Empty Domain CFD Simulation",
      "doc": [
          "weuq-0015/README.rst",   
          "weuq-0015/figures/we15_domain_geometry.svg",
          "weuq-0015/figures/we15_start_tab.svg",
          "weuq-0015/figures/we15_geometry_tab.svg",
          "weuq-0015/figures/we15_mesh_tab.svg",
          "weuq-0015/figures/we15_numerical_setup_tab.svg",
          "weuq-0015/figures/we15_monitoring_tab.svg",
          "weuq-0015/figures/we15_results_tab.svg",
          "weuq-0015/figures/we15_results_prof.svg",
          "weuq-0015/figures/we15_results_pressure.svg",
          "weuq-0015/figures/we15_results_spectra.svg",
          "weuq-0015/figures/we15_results_flow_vis.svg",
          "weuq-0015/figures/we15_run_job.svg"
      ],
      "entry_point": "weuq-0015/./input.json",
      "summary": "This example demonstrates application of CFD for characterize Atmospheric Boundary Layer (ABL) flows using large-eddy simulation (LES).",
      "logo": "we14_CFD_Results_StreamLines.svg",
      "published": "2023-09-12T21:30:53.946381-08:00\"",
      "categories": {
        "Difficulty": "0",
        "Simulation": "OpenSees-Simulation"
      },
      "tags": [
      ]
    },
    "weuq-0016": {
      "id": "weuq-0016",
      "base": "weuq-0016",
      "title": "Wind-tunnel-informed Stochastic Wind Pressure Generator",
      "doc": [
          "weuq-0016/README.rst"
      ],
      "entry_point": "weuq-0016/./input.json",
      "summary": "This example generates multiple pressure time histories using single experimental time history and performs structural analysis",
      "logo": "",
      "published": "2024-04-20T21:30:53.946381-08:00\"",
      "categories": {
        "Difficulty": "0",
        "Simulation": "OpenSees-Simulation"
      },
      "tags": [
      ]
    }
  },
  "categories": {
    "Difficulty": {
      "0": "Beginner",
      "1": "Intermediate",
      "2": "Advanced"
    },
    "Simulation": {
      "IMasEDP": "IMasEDP",
      "OpenSees-Simulation": "OpenSees",
      "OpenSeesPy-Simulation": "OpenSeesPy"
    }
  }
}
